mDUELink/__init__.py
mDUELink/analog.py
mDUELink/button.py
mDUELink/digital.py
mDUELink/duelinklib.py
mDUELink/frequency.py
mDUELink/graphics.py
mDUELink/i2c.py
mDUELink/led.py
mDUELink/sound.py
mDUELink/system.py
mDUELink/transport.py
mDUELink-0.0.3.dist-info/METADATA
mDUELink-0.0.3.dist-info/WHEEL
mDUELink-0.0.3.dist-info/top_level.txt
mDUELink-0.0.3.dist-info/RECORD
