Metadata-Version: 2.1
Name: mDUELink
Version: 0.0.3
Summary: GHI Electronics DUELink MicroPython library.
Home-page: https://www.duelink.com/
Author: GHI Electronics
Author-email: support@ghielectronics.com
License: MIT
Classifier: Programming Language :: Python :: Implementation :: MicroPython
